aisegcell/__init__.py
aisegcell/_version.py
aisegcell/aisegcell.py
aisegcell/models/__init__.py
aisegcell/models/unet.py
aisegcell/models/_test/__init__.py
aisegcell/models/_test/test_unet.py
aisegcell/preprocessing/__init__.py
aisegcell/preprocessing/generate_list.py
aisegcell/preprocessing/_tests/__init__.py
aisegcell/preprocessing/_tests/test_generate_list.py
aisegcell/utils/__init__.py
aisegcell/utils/callbacks.py
aisegcell/utils/datamodule.py
aisegcell/utils/evaluation.py
aisegcell/utils/_tests/__init__.py
aisegcell/utils/_tests/test_utils_dataset.py
aisegcell/utils/_tests/test_utils_evaluation.py
aisegcell-0.2.0.dist-info/LICENSE
aisegcell-0.2.0.dist-info/METADATA
aisegcell-0.2.0.dist-info/WHEEL
aisegcell-0.2.0.dist-info/entry_points.txt
aisegcell-0.2.0.dist-info/top_level.txt
aisegcell-0.2.0.dist-info/RECORD
