Metadata-Version: 2.1
Name: aisegcell
Version: 0.2.0
Summary: U-Net based cell and nucleus segmentation for brightfield microscopy
Home-page: https://github.com/CSDGroup/aisegcell
Author: Daniel Schirmacher
Author-email: dschirethz@gmail.com
License: BSD-3-Clause
Project-URL: Bug Tracker, https://github.com/CSDGroup/aisegcell/issues
Project-URL: Documentation, https://github.com/CSDGroup/aisegcell#README.md
Project-URL: Source Code, https://github.com/CSDGroup/aisegcell
Project-URL: User Support, https://github.com/CSDGroup/aisegcell/issues
Classifier: Development Status :: 4 - Beta
Classifier: Intended Audience :: Developers
Classifier: License :: OSI Approved :: BSD License
Classifier: Operating System :: OS Independent
Classifier: Programming Language :: Python
Classifier: Programming Language :: Python :: 3
Classifier: Programming Language :: Python :: 3.7
Classifier: Programming Language :: Python :: 3.8
Classifier: Programming Language :: Python :: 3.9
Classifier: Topic :: Scientific/Engineering :: Artificial Intelligence
Classifier: Topic :: Scientific/Engineering :: Bio-Informatics
Requires-Python: >=3.7
License-File: LICENSE
Requires-Dist: matplotlib
Requires-Dist: numpy
Requires-Dist: pandas
Requires-Dist: scikit-image
Provides-Extra: dev
Requires-Dist: pre-commit >=2.9.0 ; extra == 'dev'
Requires-Dist: check-manifest >=0.42 ; extra == 'dev'
Requires-Dist: tox ; extra == 'dev'
Requires-Dist: pytest ; extra == 'dev'
Requires-Dist: pytest-cov ; extra == 'dev'
